Config/setting.py
simutil/App.py
simutil/Async.py
simutil/ConfigParser.py
simutil/Env.py
simutil/Log.py
simutil/Oss.py
simutil/Path.py
simutil/RabbitMQ.py
simutil/Redis.py
simutil/Request.py
simutil/__init__.py
simutil/Scaffold/Artisan.py
simutil/Scaffold/basemodel.txt
simutil/Scaffold/model.txt
simutil-1.1.2.dist-info/LICENSE
simutil-1.1.2.dist-info/METADATA
simutil-1.1.2.dist-info/WHEEL
simutil-1.1.2.dist-info/top_level.txt
simutil-1.1.2.dist-info/RECORD
